simple_rag/__init__.py
simple_rag/core.py
simple_rag_pranav-0.1.0.dist-info/METADATA
simple_rag_pranav-0.1.0.dist-info/WHEEL
simple_rag_pranav-0.1.0.dist-info/top_level.txt
simple_rag_pranav-0.1.0.dist-info/RECORD
